loggingontips/InvalidFileException.py
loggingontips/LogLevels.py
loggingontips/Logger.py
loggingontips/__init__.py
loggingontips/utils.py
loggingontips-0.1.2.dist-info/LICENSE
loggingontips-0.1.2.dist-info/METADATA
loggingontips-0.1.2.dist-info/WHEEL
loggingontips-0.1.2.dist-info/top_level.txt
loggingontips-0.1.2.dist-info/RECORD
