Metadata-Version: 2.1
Name: loggingontips
Version: 0.1.2
Summary: loggingontips is a library which makes logging flexible and easy to use without bothering about log management.
Home-page: https://github.com/tanishq0917t/loggingontips
Author: Tanishq Rawat
Author-email: tanishqrawat8@gmail.com
License: MIT
Classifier: Programming Language :: Python :: 3
Classifier: License :: OSI Approved :: MIT License
Classifier: Operating System :: OS Independent
Requires-Python: >=3.6
License-File: LICENSE
